LICENSE
MANIFEST.in
README
metals.sh
setup.cfg
setup.py
metals/__init__.py
metals/metals.py
metals/opensubtitleshashing.py
metals.egg-info/PKG-INFO
metals.egg-info/SOURCES.txt
metals.egg-info/dependency_links.txt
metals.egg-info/entry_points.txt
metals.egg-info/requires.txt
metals.egg-info/top_level.txt
metals.egg-info/zip-safe