Metadata-Version: 1.0
Name: metals
Version: 0.1.1dev
Summary: list metadata for (movie) files on the command line
Home-page: http://code.google.com/p/metals/
Author: David
Author-email: dayf@gmx.net
License: MIT
Keywords: metadata imdb ls
Platform: UNKNOWN
Classifier: Development Status :: 4 - Beta
Classifier: Environment :: Console
Classifier: Intended Audience :: Education
Classifier: License :: OSI Approved :: MIT License
Classifier: Operating System :: POSIX :: Linux
Classifier: Programming Language :: Python
Classifier: Topic :: Documentation
Classifier: Topic :: Utilities
